fds/__init__.py
fds/sdk/__init__.py
fds/sdk/ChartGenerationService/__init__.py
fds/sdk/ChartGenerationService/api_client.py
fds/sdk/ChartGenerationService/configuration.py
fds/sdk/ChartGenerationService/exceptions.py
fds/sdk/ChartGenerationService/model_utils.py
fds/sdk/ChartGenerationService/rest.py
fds/sdk/ChartGenerationService/api/__init__.py
fds/sdk/ChartGenerationService/api/chart_templates_api.py
fds/sdk/ChartGenerationService/apis/__init__.py
fds/sdk/ChartGenerationService/model/__init__.py
fds/sdk/ChartGenerationService/model/categories_error_response.py
fds/sdk/ChartGenerationService/model/categorized_chart_list.py
fds/sdk/ChartGenerationService/model/category_chart_list_error_object.py
fds/sdk/ChartGenerationService/model/category_list_response.py
fds/sdk/ChartGenerationService/model/chart_error_response_object.py
fds/sdk/ChartGenerationService/model/chart_input.py
fds/sdk/ChartGenerationService/model/chart_list.py
fds/sdk/ChartGenerationService/model/chart_list_error_response.py
fds/sdk/ChartGenerationService/model/error_response.py
fds/sdk/ChartGenerationService/model/unauthorized_response.py
fds/sdk/ChartGenerationService/models/__init__.py
fds.sdk.ChartGenerationService-0.21.15.dist-info/LICENSE
fds.sdk.ChartGenerationService-0.21.15.dist-info/METADATA
fds.sdk.ChartGenerationService-0.21.15.dist-info/WHEEL
fds.sdk.ChartGenerationService-0.21.15.dist-info/top_level.txt
fds.sdk.ChartGenerationService-0.21.15.dist-info/RECORD
